{
  "chapter": "市场分析与商业模式",
  "description": "市场与商业模式章节国奖话术模板库",
  "sentence_patterns": {
    "business_model_naming": [
      "本项目采用'XX+YY+ZZ'三位一体的商业模式，构建了从技术到产品的完整商业闭环。",
      "在商业模式上，我们设计了'XX驱动、YY变现、ZZ增值'的三级火箭模型。",
      "参考了XX行业头部企业的成功经验，我们构建了'以XX为核心、以YY为延伸、以ZZ为增值'的商业体系。"
    ],
    "revenue_stream_detail": [
      "第一层（核心层）：面向XX客户提供YY产品，该部分预计占总营收的ZZ%，目标客户包括AA、BB等头部品牌。",
      "第二层（延伸层）：针对XX领域的YY需求，提供定制化ZZ方案，已与AA达成初步合作意向，预计贡献BB%营收。",
      "第三层（增值层）：为XX行业提供系统级解决方案，通过服务费和订阅制实现持续性收入。"
    ],
    "customer_evidence": [
      "目前已与XX、XX等头部企业达成合作/试用意向，累计获得YY万元意向订单。",
      "产品已在XX场景下完成落地验证，客户反馈满意度达到YY%。",
      "现有客户包括XX领域的XX家标杆企业，覆盖了YY至ZZ的完整产业链。"
    ],
    "market_sizing": [
      "根据TAM-SAM-SOM模型测算，目标市场总规模（TAM）约为XX亿元，可获取市场（SOM）约为YY亿元。",
      "XX市场正处于快速增长期，预计202X-202X年间将保持XX%的复合年增长率。",
      "参照海外市场渗透率（XX%），国内对应市场还存在YY倍以上的增长空间。"
    ],
    "swot_analysis": [
      "优势（S）：技术壁垒高、团队配置优、先发优势明显。",
      "劣势（W）：品牌知名度待提升、资金规模有限。",
      "机会（O）：政策利好、进口替代需求旺盛、市场空间巨大。",
      "威胁（T）：巨头进入可能、技术迭代风险、人才竞争激烈。"
    ],
    "closing_summary": [
      "通过'以XX为切入口，以YY为增长极，以ZZ为护城河'的路径，构建了可持续的商业闭环。",
      "综上所述，本项目的商业模式具有清晰性、可复制性和高成长性三大特征。"
    ]
  },
  "connectors": [
    "从盈利角度来看...",
    "进一步拆解收入结构...",
    "与竞品模式对比来看...",
    "长期来看...",
    "值得注意的是..."
  ],
  "must_include_keywords": [
    "商业闭环", "收入模型", "客户验证", "市场渗透",
    "增长曲线", "盈利模式", "竞争优势", "可复制性"
  ]
}
